j2rt/__init__.py
j2rt/__main__.py
j2rt/custom_filters.py
j2rt/main.py
j2rt/version.py
j2rt-0.2.0.dist-info/LICENSE
j2rt-0.2.0.dist-info/METADATA
j2rt-0.2.0.dist-info/WHEEL
j2rt-0.2.0.dist-info/entry_points.txt
j2rt-0.2.0.dist-info/top_level.txt
j2rt-0.2.0.dist-info/RECORD
