Metadata-Version: 2.1
Name: j2rt
Version: 0.2.0
Summary: Jinja2 rendering tool
Home-page: https://github.com/slashbeast/j2rt
Author: Piotr Karbowski
License: BSD
Download-URL: https://github.com/slashbeast/j2rt/archive/v0.2.0.tar.gz
Platform: UNKNOWN
Requires-Dist: jinja2
Requires-Dist: boto3
Requires-Dist: python-gnupg
